podns/__init__.py
podns/dns.py
podns/error.py
podns/parser.py
podns/pronouns.py
podns/py.typed
podns-0.2.2.dist-info/METADATA
podns-0.2.2.dist-info/WHEEL
podns-0.2.2.dist-info/licenses/LICENSE
podns-0.2.2.dist-info/RECORD
