Metadata-Version: 2.4
Name: podns
Version: 0.2.2
Summary: A Pronouns over DNS specification compliant Python API.
License: MIT
License-File: LICENSE
Author: abigail phoebe
Author-email: abigail@phoebe.sh
Requires-Python: >=3.14
Classifier: License :: OSI Approved :: MIT License
Classifier: Programming Language :: Python :: 3
Classifier: Programming Language :: Python :: 3.14
Requires-Dist: dnspython (>=2.8.0)
Project-URL: Bug Tracker, https://github.com/ijsbol/podns_py/issues
Project-URL: Homepage, https://github.com/ijsbol/podns_py
